file_scraper/main.py
file_scraper/fonts/FiraCode-Medium.woff2
file_scraper/reports/default.html
file_scraper/templates/default.json
file_scraper/utils/array.py
file_scraper/utils/config.py
file_scraper/utils/directory.py
file_scraper/utils/file.py
file_scraper/utils/general.py
file_scraper/utils/grep.py
file_scraper/utils/jquery.py
file_scraper/utils/rabin.py
file_scraper/utils/report.py
file_scraper/utils/result.py
file_scraper/utils/scrape.py
file_scraper/utils/stopwatch.py
file_scraper/utils/string.py
file_scraper/utils/template.py
file_scraper/utils/validate.py
file_scraper-4.7.dist-info/licenses/LICENSE
file_scraper-4.7.dist-info/METADATA
file_scraper-4.7.dist-info/WHEEL
file_scraper-4.7.dist-info/entry_points.txt
file_scraper-4.7.dist-info/top_level.txt
file_scraper-4.7.dist-info/RECORD
