Metadata-Version: 2.4
Name: file-scraper
Version: 4.7
Summary: Scrape files for sensitive information, and generate an interactive HTML report.
Author: Ivan Sincek
Project-URL: Homepage, https://github.com/ivan-sincek/file-scraper
Classifier: Programming Language :: Python :: 3
Classifier: License :: OSI Approved :: MIT License
Classifier: Operating System :: OS Independent
Requires-Python: >=3.10
License-File: LICENSE
Requires-Dist: alive-progress>=3.1.5
Requires-Dist: beautifulsoup4>=4.12.3
Requires-Dist: colorama>=0.4.6
Requires-Dist: jsbeautifier>=1.14.11
Requires-Dist: pyOpenSSL>=24.0.0
Requires-Dist: regex>=2023.8.8
Requires-Dist: termcolor>=2.4.0
Dynamic: license-file
